karstnet/__init__.py
karstnet/base.py
karstnet/import_fc.py
karstnet-1.2.5.dist-info/LICENSE
karstnet-1.2.5.dist-info/METADATA
karstnet-1.2.5.dist-info/WHEEL
karstnet-1.2.5.dist-info/top_level.txt
karstnet-1.2.5.dist-info/RECORD
