Metadata-Version: 2.1
Name: karstnet
Version: 1.2.5
Summary: Statistical characterization of karst networks
Author-email: Philippe Renard <philippe.renard@unine.ch>, Pauline Collon <pauline.collon@univ-lorraine.fr>
License: MIT License
Project-URL: Documentation, https://karstnet.readthedocs.org
Project-URL: Repository, https://github.com/karstnet/karstnet
Project-URL: Issues, https://github.com/karstnet/karstnet/issues
Keywords: geomorphology,karst,graph,statistics
Classifier: Programming Language :: Python :: 3
Classifier: License :: OSI Approved :: MIT License
Classifier: Operating System :: OS Independent
Requires-Python: >=3.8
License-File: LICENSE
Requires-Dist: numpy
Requires-Dist: matplotlib
Requires-Dist: networkx
Requires-Dist: scipy
Requires-Dist: mplstereonet
Provides-Extra: dev
Requires-Dist: pycodestyle ; extra == 'dev'
Requires-Dist: pytest ; extra == 'dev'
Requires-Dist: pytest-cov ; extra == 'dev'
Requires-Dist: coveralls ; extra == 'dev'
Requires-Dist: sphynx ; extra == 'dev'
Requires-Dist: numpydoc ; extra == 'dev'
Requires-Dist: sphinx-rtd-theme ; extra == 'dev'
Requires-Dist: build ; extra == 'dev'
Requires-Dist: twine ; extra == 'dev'
